<?xml version="1.0"?>
<runHistory script="aaa1navElec">
 <run>
  <RunDate>2020-08-21 11:30:18.899 -0500</RunDate>
  <Status>Success</Status>
  <Duration>2.961545</Duration>
  <Errors>0</Errors>
  <Warnings>0</Warnings>
  <Exceptions>0</Exceptions>
  <Successes>1</Successes>
  <LogFile>20200821_113018.899/LogFile.txt</LogFile>
  <ReturnValue></ReturnValue>
  <ErrorMessage></ErrorMessage>
 </run>
 <run>
  <RunDate>2020-08-21 11:32:02.108 -0500</RunDate>
  <Status>Success</Status>
  <Duration>16.722764</Duration>
  <Errors>0</Errors>
  <Warnings>0</Warnings>
  <Exceptions>0</Exceptions>
  <Successes>1</Successes>
  <LogFile>20200821_113202.108/LogFile.txt</LogFile>
  <ReturnValue></ReturnValue>
  <ErrorMessage></ErrorMessage>
 </run>
 <run>
  <RunDate>2020-08-21 11:32:20.602 -0500</RunDate>
  <Status>Success</Status>
  <Duration>16.762138</Duration>
  <Errors>0</Errors>
  <Warnings>0</Warnings>
  <Exceptions>0</Exceptions>
  <Successes>1</Successes>
  <LogFile>20200821_113220.602/LogFile.txt</LogFile>
  <ReturnValue></ReturnValue>
  <ErrorMessage></ErrorMessage>
 </run>
</runHistory>
