{
  "entries" : [
    {
      "identifier" : "START",
      "message" : "Running GetStockPrice.apitest",
      "timestamp" : "2020-06-24 14:39:38.003 -0500"
    },
    {
      "handlerName" : "on_getstockprice",
      "message" : "Assertion Succeeded:  (assertion: api().statusCode is 200; true: 200 IS equal to 200)",
      "timestamp" : "2020-06-24 14:39:38.681 -0500",
      "identifier" : "LogSuccess",
      "scriptName" : "\/Users\/mikefey\/Documents\/EggplantSuites\/nopCommerce.suite\/APITests\/GetStockPrice.apitest",
      "handlerLine" : 4
    },
    {
      "handlerName" : "on_getstockprice",
      "message" : "\"close\":6.15",
      "timestamp" : "2020-06-24 14:39:38.726 -0500",
      "identifier" : "Log",
      "scriptName" : "\/Users\/mikefey\/Documents\/EggplantSuites\/nopCommerce.suite\/APITests\/GetStockPrice.apitest",
      "handlerLine" : 11
    },
    {
      "handlerName" : "on_getstockprice",
      "message" : "6.15",
      "timestamp" : "2020-06-24 14:39:38.751 -0500",
      "identifier" : "Log",
      "scriptName" : "\/Users\/mikefey\/Documents\/EggplantSuites\/nopCommerce.suite\/APITests\/GetStockPrice.apitest",
      "handlerLine" : 13
    },
    {
      "handlerName" : "on_getstockprice",
      "message" : "\"symbol\":\"F\"",
      "timestamp" : "2020-06-24 14:39:38.787 -0500",
      "identifier" : "Log",
      "scriptName" : "\/Users\/mikefey\/Documents\/EggplantSuites\/nopCommerce.suite\/APITests\/GetStockPrice.apitest",
      "handlerLine" : 16
    },
    {
      "handlerName" : "on_getstockprice",
      "message" : "F",
      "timestamp" : "2020-06-24 14:39:38.807 -0500",
      "identifier" : "Log",
      "scriptName" : "\/Users\/mikefey\/Documents\/EggplantSuites\/nopCommerce.suite\/APITests\/GetStockPrice.apitest",
      "handlerLine" : 19
    },
    {
      "identifier" : "EndTestCase",
      "message" : "(Duration:\"4.487718\", Errors:\"0\", Exceptions:\"0\", StartTime:\"2020-06-24 14:39:38 -0500\", Successes:\"1\", TestCase:\"GetStockPrice.apitest\", Warnings:\"0\")",
      "timestamp" : "2020-06-24 14:39:42.495 -0500"
    },
    {
      "identifier" : "SUCCESS",
      "message" : "Execution Time 0:00:04 GetStockPrice.apitest",
      "timestamp" : "2020-06-24 14:39:42.594 -0500"
    }
  ],
  "createdTimestamp" : "2020-06-24 14:39:38.006 -0500"
}