{
  "entries" : [
    {
      "message" : "Running emr\/zzzEMRLogin.script",
      "timestamp" : "2020-11-02 17:16:57.799 -0600",
      "identifier" : "START",
      "handlerLine" : 1,
      "handlerName" : "execute string"
    },
    {
      "handlerName" : "on_emr_zzzemrlogin",
      "message" : "Login with: admin",
      "timestamp" : "2020-11-02 17:16:57.842 -0600",
      "identifier" : "Log",
      "scriptName" : "emr\/zzzEMRLogin.script",
      "handlerLine" : 3
    },
    {
      "handlerName" : "on_emr_zzzemrlogin",
      "message" : "Password is: pass",
      "timestamp" : "2020-11-02 17:16:57.854 -0600",
      "identifier" : "Log",
      "scriptName" : "emr\/zzzEMRLogin.script",
      "handlerLine" : 4
    },
    {
      "handlerName" : "on_emr_zzzemrlogin",
      "message" : "admin",
      "timestamp" : "2020-11-02 17:16:57.922 -0600",
      "identifier" : "typetext",
      "scriptName" : "emr\/zzzEMRLogin.script",
      "handlerLine" : 7
    },
    {
      "handlerName" : "on_emr_zzzemrlogin",
      "message" : "[tab]",
      "timestamp" : "2020-11-02 17:16:58.639 -0600",
      "identifier" : "typetext",
      "scriptName" : "emr\/zzzEMRLogin.script",
      "handlerLine" : 8
    },
    {
      "handlerName" : "on_emr_zzzemrlogin",
      "message" : "pass",
      "timestamp" : "2020-11-02 17:16:59.436 -0600",
      "identifier" : "typetext",
      "scriptName" : "emr\/zzzEMRLogin.script",
      "handlerLine" : 9
    },
    {
      "handlerName" : "on_emr_zzzemrlogin",
      "message" : "[returnKey]",
      "timestamp" : "2020-11-02 17:17:00.156 -0600",
      "identifier" : "typetext",
      "scriptName" : "emr\/zzzEMRLogin.script",
      "handlerLine" : 10
    },
    {
      "handlerName" : "on_emr_zzzemrlogin",
      "message" : "EMR was loaded ",
      "timestamp" : "2020-11-02 17:17:04.166 -0600",
      "identifier" : "Log",
      "scriptName" : "emr\/zzzEMRLogin.script",
      "handlerLine" : 13
    },
    {
      "message" : "(Duration:\"6.370954\", Errors:\"0\", Exceptions:\"0\", StartTime:\"2020-11-02 17:16:57 -0600\", Successes:\"1\", TestCase:\"emr\/zzzEMRLogin.script\", Warnings:\"0\")",
      "timestamp" : "2020-11-02 17:17:04.172 -0600",
      "identifier" : "EndTestCase",
      "handlerLine" : 1,
      "handlerName" : "execute string"
    },
    {
      "message" : "Execution Time 0:00:06 emr\/zzzEMRLogin.script",
      "timestamp" : "2020-11-02 17:17:04.320 -0600",
      "identifier" : "SUCCESS",
      "handlerLine" : 1,
      "handlerName" : "execute string"
    }
  ],
  "createdTimestamp" : "2020-11-02 17:16:57.800 -0600"
}