{
  "entries" : [
    {
      "message" : "Running go2Login.script",
      "timestamp" : "2020-07-14 14:26:27.024 -0500",
      "identifier" : "START",
      "handlerLine" : 1,
      "handlerName" : "execute string"
    },
    {
      "handlerName" : "on_backtotop",
      "message" : "[homeKey]",
      "timestamp" : "2020-07-14 14:26:27.049 -0500",
      "identifier" : "typetext",
      "scriptName" : "Utilities.script",
      "handlerLine" : 2
    },
    {
      "handlerName" : "on_backtotop",
      "message" : "found at (392, 181)",
      "identifier" : "waitfor",
      "image" : "NopCommerce_Logo",
      "handlerLine" : 3,
      "timestamp" : "2020-07-14 14:26:27.690 -0500",
      "scriptName" : "Utilities.script"
    },
    {
      "handlerName" : "on_go2login",
      "message" : "found at (86, 50)",
      "identifier" : "waitfor",
      "image" : "RefreshButton.png",
      "handlerLine" : 3,
      "timestamp" : "2020-07-14 14:26:28.193 -0500",
      "scriptName" : "go2Login.script"
    },
    {
      "handlerName" : "on_go2login",
      "message" : "at (1278, 92)",
      "identifier" : "click",
      "image" : "go2loginCommerce",
      "handlerLine" : 6,
      "timestamp" : "2020-07-14 14:26:28.801 -0500",
      "scriptName" : "go2Login.script"
    },
    {
      "message" : "(Duration:\"1.778465\", Errors:\"0\", Exceptions:\"0\", StartTime:\"2020-07-14 14:26:27 -0500\", Successes:\"1\", TestCase:\"go2Login.script\", Warnings:\"0\")",
      "timestamp" : "2020-07-14 14:26:28.807 -0500",
      "identifier" : "EndTestCase",
      "handlerLine" : 1,
      "handlerName" : "execute string"
    },
    {
      "message" : "Execution Time 0:00:01 go2Login.script",
      "timestamp" : "2020-07-14 14:26:28.899 -0500",
      "identifier" : "SUCCESS",
      "handlerLine" : 1,
      "handlerName" : "execute string"
    }
  ],
  "createdTimestamp" : "2020-07-14 14:26:27.027 -0500"
}