{
  "entries" : [
    {
      "message" : "Running NavDesktop.script",
      "timestamp" : "2020-08-21 10:58:14.947 -0500",
      "identifier" : "START",
      "handlerLine" : 1,
      "handlerName" : "execute string"
    },
    {
      "handlerName" : "on_navdesktop",
      "message" : "at (194, 1023)",
      "identifier" : "tap",
      "image" : "CATEGORIES",
      "handlerLine" : 10,
      "timestamp" : "2020-08-21 10:58:16.780 -0500",
      "scriptName" : "NavDesktop.script"
    },
    {
      "handlerName" : "on_navdesktop",
      "message" : "at (169, 1121)",
      "identifier" : "tap",
      "image" : "Computers_mobile",
      "handlerLine" : 12,
      "timestamp" : "2020-08-21 10:58:20.603 -0500",
      "scriptName" : "NavDesktop.script"
    },
    {
      "handlerName" : "on_scrolluntilfound",
      "message" : "SWIPESPEED = 10",
      "timestamp" : "2020-08-21 10:58:20.639 -0500",
      "identifier" : "set",
      "scriptName" : "MobileUtilities.script",
      "handlerLine" : 2
    },
    {
      "handlerName" : "on_scrolluntilfound",
      "message" : "Unable to Find Image mobileComputersImage",
      "identifier" : "imagefound",
      "image" : "mobileComputersImage",
      "handlerLine" : 3,
      "timestamp" : "2020-08-21 10:58:21.422 -0500",
      "scriptName" : "MobileUtilities.script"
    },
    {
      "handlerName" : "on_scrolluntilfound",
      "message" : "Swiped up from (414, 1254) to (414, 538)",
      "timestamp" : "2020-08-21 10:58:22.281 -0500",
      "identifier" : "swipeup",
      "scriptName" : "MobileUtilities.script",
      "handlerLine" : 1
    },
    {
      "handlerName" : "on_scrolluntilfound",
      "message" : "found at (404, 1166)",
      "identifier" : "imagefound",
      "image" : "mobileComputersImage",
      "handlerLine" : 11,
      "timestamp" : "2020-08-21 10:58:26.731 -0500",
      "scriptName" : "MobileUtilities.script"
    },
    {
      "handlerName" : "on_navdesktop",
      "message" : "at (404, 1166)",
      "identifier" : "tap",
      "image" : "mobileComputersImage",
      "handlerLine" : 14,
      "timestamp" : "2020-08-21 10:58:27.035 -0500",
      "scriptName" : "NavDesktop.script"
    },
    {
      "message" : "(Duration:\"12.093053\", Errors:\"0\", Exceptions:\"0\", StartTime:\"2020-08-21 10:58:14 -0500\", Successes:\"1\", TestCase:\"NavDesktop.script\", Warnings:\"0\")",
      "timestamp" : "2020-08-21 10:58:27.042 -0500",
      "identifier" : "EndTestCase",
      "handlerLine" : 1,
      "handlerName" : "execute string"
    },
    {
      "message" : "Execution Time 0:00:12 NavDesktop.script",
      "timestamp" : "2020-08-21 10:58:27.196 -0500",
      "identifier" : "SUCCESS",
      "handlerLine" : 1,
      "handlerName" : "execute string"
    }
  ],
  "createdTimestamp" : "2020-08-21 10:58:14.949 -0500"
}